dt_tools/__init__.py
dt_tools/cli/demos/dt_console_demo.py
dt_tools/cli/demos/dt_console_helper_demo.py
dt_tools/cli/demos/dt_console_input_helper_demo.py
dt_tools/cli/demos/dt_msgbox_demo.py
dt_tools/cli/demos/dt_progress_bar_demo.py
dt_tools/cli/demos/dt_spinner_demo.py
dt_tools/console/__init__.py
dt_tools/console/console_helper.py
dt_tools/console/msgbox.py
dt_tools/console/progress_bar.py
dt_tools/console/spinner.py
dt_console-0.1.26.dist-info/LICENSE
dt_console-0.1.26.dist-info/METADATA
dt_console-0.1.26.dist-info/WHEEL
dt_console-0.1.26.dist-info/RECORD
