Metadata-Version: 2.3
Name: dt-console
Version: 0.1.26
Summary: Console helper tools for CLIs
License: MIT
Keywords: python,dt-tools,cli,console,command-line,status bar,progress bar
Author: Al DAmico
Author-email: JavaWiz1@hotmail.com
Requires-Python: >=3.10,<4.0
Classifier: License :: OSI Approved :: MIT License
Classifier: Programming Language :: Python
Classifier: Programming Language :: Python :: 3
Classifier: Programming Language :: Python :: 3.10
Classifier: Programming Language :: Python :: 3.11
Classifier: Programming Language :: Python :: 3.12
Classifier: Programming Language :: Python :: 3.13
Requires-Dist: dt-foundation
Project-URL: Repository, https://github.com/JavaWiz1/dt-console
